qcheck/__init__.py
qcheck/conversion.py
qcheck/decorators.py
qcheck/error.py
qcheck/exceptions.py
qcheck/location.py
qcheck/run_check.py
qcheck-0.1.0.dist-info/WHEEL
qcheck-0.1.0.dist-info/METADATA
qcheck-0.1.0.dist-info/RECORD
