Metadata-Version: 2.1
Name: qcheck
Version: 0.1.0
Summary: Simple way to validate data structures
License: MIT
Author: miphreal
Author-email: miphreal@gmail.com
Requires-Python: >=3.6,<3.9
Classifier: License :: OSI Approved :: MIT License
Classifier: Programming Language :: Python :: 3
Classifier: Programming Language :: Python :: 3.6
Classifier: Programming Language :: Python :: 3.7
Classifier: Programming Language :: Python :: 3.8
